{
  "IM_username": "Nom d'utilisateur ",
  "IM_network_error": "Réseau indisponible!",
  "IM_login": "Connectez-vous maintenant",
  "IM_send": "Envoyer",
  "IM_no_more": "Il n'y a plus de messages historiques",
  "IM_username_error": "Erreur du nom d'utilisateur ou mot de passe",
  "IM_password": "Mot de passe",
  "IM_try_again": "Toucher pour charger à nouveau ",
  "IM_get_more": "Charger plus",
  "update": "Examiner le renouvellement ",
  "send": "Envoyer",
  "new_guid": "Guide de novice:",
  "set": "Réglages",
  "send_img": "Envoyer des photos",
  "check_network": "Réseau indisponible, vérifiez votre réseau",
  "username_hd": "Veuillez entrer le nom d'utilisateur",
  "16chat": "16Chat1.0",
  "friendchat": "Aucun ami sélectionné pour le chat",
  "network": "Réseau indisponible! Veuillez",
  "version": "Informations de version",
  "username": "Il est nécessaire pour vous d'entrer le nom de l'utilisateur.",
  "retry_Click": "Cliquez pour réessayer",
  "pwd_hd": "Veuillez entrer le mot de passe",
  "sys_lan": "Langue:",
  "no_friend": "Vous n'avez pas choisi l'ami, ne pouvez pas envoyer le message maintenant",
  "trans_err": "Erreur de traduction",
  "notice": "Notification hors ligne",
  "pwd_err": "Le mot de passe est faux.",
  "copy": "Copier",
  "sure": "OK",
  "send_msg": "Impossible d'envoyer un message vide",
  "screenshot": "Scan",
  "trans_lan": "Langue de traduction",
  "username_err": "Erreur d'entrée du nom d'utilisateur",
  "enter": "Nouvelle ligne",
  "forget_pwd": "Oublier le mot de passe",
  "more_msg": "Charger plus",
  "history": "Chargement des information historiques",
  "register": "Inscription",
  "connect_err": "Réseau indisponible, cliquez pour inscrire ",
  "trans": "Traduction",
  "pwd": "Le mot de passe ne peut pas être vide",
  "msg_length": "La longueur du message dépasse la limite (Jusqu'à 1000 caractère chinois)",
  "see": "Voir ",
  "off": "Annuler",
  "rem_pwd": "Retenir le mot de passe",
  "hot_set": "Remettre un raccourci clavier :",
  "del_mdir": "Êtes-vous sûr de supprimer le compte de la liste?",
  "timeout": "Délai d'attente du réseau de !",
  "hotSet": "Créer un bouton directement ",
  "change_lan":"changement"
}